[
  {
    "quote": "إِنَّ مَعَ الْعُسْرِ يُسْرًا",
    "author": "سورة الشرح"
  },
  {
    "quote": "وَمَن يَتَوَكَّلْ عَلَى اللَّهِ فَهُوَ حَسْبُهُ",
    "author": "سورة الطلاق"
  },
  {
    "quote": "فَاذْكُرُونِي أَذْكُرْكُمْ",
    "author": "سورة البقرة"
  },
  {
    "quote": "لَا يُكَلِّفُ اللَّهُ نَفْسًا إِلَّا وُسْعَهَا",
    "author": "سورة البقرة"
  },
  {
    "quote": "وَمَا تَوْفِيقِي إِلَّا بِاللَّهِ",
    "author": "سورة هود"
  },
  {
    "quote": "إِنَّ اللَّهَ مَعَ الصَّابِرِينَ",
    "author": "سورة البقرة"
  },
  {
    "quote": "وَاصْبِرْ لِحُكْمِ رَبِّكَ فَإِنَّكَ بِأَعْيُنِنَا",
    "author": "سورة الطور"
  },
  {
    "quote": "قُل لَّن يُصِيبَنَا إِلَّا مَا كَتَبَ اللَّهُ لَنَا",
    "author": "سورة التوبة"
  },
  {
    "quote": "وَقُل رَّبِّ زِدْنِي عِلْمًا",
    "author": "سورة طه"
  },
  {
    "quote": "فَإِنِّي قَرِيبٌ أُجِيبُ دَعْوَةَ الدَّاعِ إِذَا دَعَانِ",
    "author": "سورة البقرة"
  }
]
